unv2ccx/FEM.py
unv2ccx/INPWriter.py
unv2ccx/UNVParser.py
unv2ccx/__init__.py
unv2ccx/clean.py
unv2ccx/release.py
unv2ccx-2.0.0.dist-info/LICENSE
unv2ccx-2.0.0.dist-info/METADATA
unv2ccx-2.0.0.dist-info/WHEEL
unv2ccx-2.0.0.dist-info/top_level.txt
unv2ccx-2.0.0.dist-info/RECORD
