Metadata-Version: 2.1
Name: unv2ccx
Version: 2.0.0
Summary: Salome to CalculiX converter (unv to inp)
Home-page: https://github.com/calculix/unv2ccx
Author: Ihor Mirzov
Author-email: imirzov@gmail.com
License: UNKNOWN
Platform: UNKNOWN
Classifier: Programming Language :: Python :: 3
Classifier: License :: OSI Approved :: GNU General Public License v3 (GPLv3)
Classifier: Operating System :: OS Independent
Requires-Python: >=3.6
